logic.py
sbelt.py
plots/__init__.py
plots/plot_maker.py
plots/plotting.py
sbelt/__init__.py
sbelt/logic.py
sbelt/sbelt_runner.py
sbelt/utils.py
sbelt/plots/__init__.py
sbelt/plots/plot_maker.py
sbelt/plots/plotting.py
tests/__init__.py
tests/test_logic.py
tests/test_utils.py
sbelt-1.0.1.dist-info/LICENSE
sbelt-1.0.1.dist-info/METADATA
sbelt-1.0.1.dist-info/WHEEL
sbelt-1.0.1.dist-info/entry_points.txt
sbelt-1.0.1.dist-info/top_level.txt
sbelt-1.0.1.dist-info/RECORD
