Metadata-Version: 2.1
Name: sbelt
Version: 1.0.1
Summary: A Markov-type numerical model of sediment particle transport in rivers
Home-page: https://github.com/szwiep/py_SBeLT
Author: S. Zwiep
Author-email: szwiep@sfu.ca
License: UNKNOWN
Keywords: earth science,hydrology,sediment transport
Platform: UNKNOWN
Requires-Python: >=3.6, <4
License-File: LICENSE
Requires-Dist: numpy
Requires-Dist: scipy
Requires-Dist: h5py
Requires-Dist: tqdm
Requires-Dist: matplotlib
